vecly/__init__.py
vecly/column.py
vecly/dataframe.py
vecly/vector.py
vecly-0.1.1.dist-info/licenses/LICENSE
vecly-0.1.1.dist-info/METADATA
vecly-0.1.1.dist-info/WHEEL
vecly-0.1.1.dist-info/top_level.txt
vecly-0.1.1.dist-info/RECORD
