Metadata-Version: 2.4
Name: vecly
Version: 0.1.1
Summary: Lightweight Vector/Column/DataFrame utilities
Author: wudiFE
License: MIT
Requires-Python: >=3.9
License-File: LICENSE
Requires-Dist: numpy>=1.23
Dynamic: license-file
